{
	"authHost": "http://larabbs.test",
	"authEndpoint": "/broadcasting/auth",
	"clients": [
		{
			"appId": "2997bcc0be903c94",
			"key": "21ea826180f857353d8a0de5dd33091f"
		}
	],
	"database": "redis",
	"databaseConfig": {
		"redis": {},
		"sqlite": {
			"databasePath": "/database/laravel-echo-server.sqlite"
		}
	},
	"devMode": true,
	"host": null,
	"port": "6001",
	"protocol": "http",
	"socketio": {},
	"sslCertPath": "",
	"sslKeyPath": "",
	"sslCertChainPath": "",
	"sslPassphrase": "",
	"apiOriginAllow": {
		"allowCors": false,
		"allowOrigin": "",
		"allowMethods": "",
		"allowHeaders": ""
	}
}